Metadata-Version: 2.1
Name: plotbook
Version: 0.0.7
Summary: Generate automatic plot for pandas DataFrame
Home-page: https://github.com/shifwang/plotbook
Author: Yu Wang
Author-email: shifwangonline@gmail.com
License: MIT
Keywords: pandas data-science data-analysis python jupyter ipython
Platform: UNKNOWN
Classifier: Development Status :: 5 - Production/Stable
Classifier: Topic :: Software Development :: Build Tools
Classifier: License :: OSI Approved :: MIT License
Classifier: Environment :: Console
Classifier: Operating System :: OS Independent
Classifier: Intended Audience :: Science/Research
Classifier: Intended Audience :: Developers
Classifier: Intended Audience :: Financial and Insurance Industry
Classifier: Intended Audience :: Healthcare Industry
Classifier: Topic :: Scientific/Engineering
Classifier: Framework :: IPython
Classifier: Programming Language :: Python :: 3
Classifier: Programming Language :: Python :: 3.6
Classifier: Programming Language :: Python :: 3.7
Classifier: Programming Language :: Python :: 3.8
Requires-Python: >=3.6
Provides-Extra: notebook
Provides-Extra: app
